{
  "idSave": 559,
  "isFirstSession": false,
  "language": "ru",
  "promptDone": false,
  "money": 33704,
  "newPlayerName": "Jiza",
  "countCards": 69,
  "countStones": 9,
  "tutorCompleted": true,
  "deck": [
    {
      "idx": 0,
      "count": 0,
      "lvl": 1
    },
    {
      "idx": 1,
      "count": 0,
      "lvl": 1
    },
    {
      "idx": 7,
      "count": 0,
      "lvl": 1
    },
    {
      "idx": 9,
      "count": 0,
      "lvl": 1
    },
    {
      "idx": 4,
      "count": 0,
      "lvl": 1
    }
  ],
  "inventory": [
    {
      "idx": 0,
      "count": 19,
      "lvl": 5
    },
    {
      "idx": 1,
      "count": 11,
      "lvl": 7
    },
    {
      "idx": 2,
      "count": 6,
      "lvl": 5
    },
    {
      "idx": 3,
      "count": 3,
      "lvl": 7
    },
    {
      "idx": 4,
      "count": 47,
      "lvl": 5
    },
    {
      "idx": 8,
      "count": 74,
      "lvl": 4
    },
    {
      "idx": 5,
      "count": 41,
      "lvl": 5
    },
    {
      "idx": 7,
      "count": 38,
      "lvl": 5
    },
    {
      "idx": 6,
      "count": 24,
      "lvl": 4
    },
    {
      "idx": 9,
      "count": 29,
      "lvl": 3
    },
    {
      "idx": 10,
      "count": 4,
      "lvl": 6
    }
  ],
  "exp": 24,
  "lvl": 1,
  "maxWave": 69,
  "openLevels": null
}